[
  [
    {
      "id": "8843",
      "result_home": "8",
      "result_away": "5",
      "actual": false
    },
    "Iglomen&RR",
    27,
    "",
    "non-divided-group"
  ],
  [
    {
      "id": "8843",
      "result_home": "8",
      "result_away": "5",
      "actual": false
    },
    "Boanerges",
    19,
    "",
    "non-divided-group"
  ],
  [
    {
      "id": "8843",
      "result_home": "8",
      "result_away": "5",
      "actual": false
    },
    "MK Team",
    17,
    "",
    "non-divided-group"
  ],
  [
    {
      "id": "8843",
      "result_home": "8",
      "result_away": "5",
      "actual": false
    },
    "Ukrainian Legion",
    15,
    "",
    "non-divided-group"
  ],
  [
    {
      "id": "8843",
      "result_home": "8",
      "result_away": "5",
      "actual": false
    },
    "S\u0142omniki Warriors",
    10,
    "",
    "non-divided-group"
  ],
  [
    {
      "id": "8843",
      "result_home": "8",
      "result_away": "5",
      "actual": false
    },
    "Brotherm",
    10,
    "",
    "non-divided-group"
  ],
  [
    {
      "id": "8843",
      "result_home": "8",
      "result_away": "5",
      "actual": false
    },
    "WKS",
    10,
    "",
    "non-divided-group"
  ],
  [
    {
      "id": "8843",
      "result_home": "8",
      "result_away": "5",
      "actual": false
    },
    "DRUGony",
    9,
    "",
    "non-divided-group"
  ]
]